Topsis/__init__.py
Topsis/topsis.py
TOPSIS_Parth_101983047-0.0.7.dist-info/LICENSE.txt
TOPSIS_Parth_101983047-0.0.7.dist-info/METADATA
TOPSIS_Parth_101983047-0.0.7.dist-info/WHEEL
TOPSIS_Parth_101983047-0.0.7.dist-info/top_level.txt
TOPSIS_Parth_101983047-0.0.7.dist-info/RECORD
