Metadata-Version: 2.1
Name: TOPSIS-Parth-101983047
Version: 0.0.7
Summary: A simplified package to perform TOPSIS Analysis.
Home-page: https://github.com/parth818/TOPSIS-Parth-101983047
Author: Parth Verma
Author-email: vermaparth818@gmail.com
License: UNKNOWN
Platform: UNKNOWN
Classifier: Programming Language :: Python :: 3
Classifier: License :: OSI Approved :: MIT License
Classifier: Operating System :: OS Independent
Requires-Python: >=3.6
Requires-Dist: pandas
